packages/__init__.py
packages/vishwa.py
packages/vishwa1.py
packages/vishwa3.py
vishwa_data_python-111.2.dist-info/LICENSE
vishwa_data_python-111.2.dist-info/METADATA
vishwa_data_python-111.2.dist-info/WHEEL
vishwa_data_python-111.2.dist-info/top_level.txt
vishwa_data_python-111.2.dist-info/RECORD
