Metadata-Version: 2.1
Name: vishwa_data_python
Version: 111.2
Summary: A Basic arthimetic Operators modules
Author: Vishwa
Author-email: vishwa.automationhub@gmail.com
Classifier: Programming Language :: Python :: 3
Classifier: License :: OSI Approved :: MIT License
Classifier: Operating System :: OS Independent
Requires-Python: >=3.6
License-File: LICENSE
